package_calculando/__init__.py
package_calculando/calculos_basicos.py
package_calculando-0.0.0.dist-info/METADATA
package_calculando-0.0.0.dist-info/WHEEL
package_calculando-0.0.0.dist-info/top_level.txt
package_calculando-0.0.0.dist-info/RECORD
