Metadata-Version: 2.1
Name: package-calculando
Version: 0.0.0
Summary: Calculadora com funcionalidades basicas
Home-page: https://github.com/AdrianaAndrade2203
Author: Adriana Andrade
Author-email: andrade.m.drika@gmail.com
Requires-Python: >=3.8
